MANIFEST.in
README.rst
README.txt
setup.py
panl/__init__.py
panl/custom.py
panl/telnetlib_panl.py
panl/utility.py
pypanl.egg-info/PKG-INFO
pypanl.egg-info/SOURCES.txt
pypanl.egg-info/dependency_links.txt
pypanl.egg-info/not-zip-safe
pypanl.egg-info/top_level.txt