Metadata-Version: 1.0
Name: pypanl
Version: 0.1.dev5
Summary: Support library for Panl.com API access.
Home-page: http://www.panl.com/
Author: Bruce Walker
Author-email: bruce.walker@panl.com
License: BSD
Platform: UNKNOWN
Classifier: Development Status :: 2 - Pre-Alpha
Classifier: Environment :: Other Environment
Classifier: Intended Audience :: Developers
Classifier: Intended Audience :: System Administrators
Classifier: License :: OSI Approved :: BSD License
Classifier: Operating System :: OS Independent
Classifier: Programming Language :: Python
Classifier: Topic :: System :: Monitoring
